{
  "name": "snapshot",
  "plural": "snapshots",
  "base": "PersistedModel",
  "idInjection": false,
  "options": {
    "validateUpsert": true
  },
  "properties": {
    "sid": {
      "type": "string",
      "id": true,
      "generated": false,
      "defaultFn": "uuid"
    },
    "name": {
      "type": "string"
    },
    "url": {
      "type": "string"
    },
    "downloadUrl": {
      "type": "string"
    },
    "lat": {
      "type": "number"
    },
    "lng": {
      "type": "number"
    },
    "fov": {
      "type": "number"
    },
    "width": {
      "type": "number"
    },
    "height": {
      "type": "number"
    },
    "createdBy": {
      "type": "string"
    },
    "modifiedBy": {
      "type": "string"
    },
    "created": {
      "type": "date"
    },
    "modified": {
      "type": "date"
    }
  },
  "validations": [],
  "relations": {
    "post": {
      "type": "belongsTo",
      "model": "post",
      "foreignKey": "postId"
    },
    "node": {
      "type": "belongsTo",
      "model": "nodemeta",
      "foreignKey": "nodeId"
    }
  },
  "acls": [],
  "methods": {}
}
